{
    "dt": 1715684400,
    "sunrise": 1715659793,
    "sunset": 1715714651,
    "moonrise": 1715679360,
    "moonset": 1715648520,
    "moon_phase": 0.22,
    "temp": {
        "day": 14.01,
        "min": 12.75,
        "max": 18.48,
        "night": 12.75,
        "eve": 13.53,
        "morn": 15.35
    },
    "feels_like": {
        "day": 13.89,
        "night": 12.59,
        "eve": 13.26,
        "morn": 15.42
    },
    "pressure": 1005,
    "humidity": 93,
    "dew_point": 12.9,
    "wind_speed": 4.33,
    "wind_deg": 185,
    "wind_gust": 12.51,
    "weather": [
        {
            "id": 501,
            "main": "Rain",
            "description": "moderate rain",
            "icon": "10d"
        }
    ],
    "clouds": 75,
    "pop": 1,
    "rain": 9.06,
    "uvi": 1.89
}